ulid_tool/__init__.py
ulid_tool/ulid/__init__.py
ulid_tool/utils/__init__.py
ulid_tool/utils/base32.py
ulid_tool/utils/baseinterface.py
ulid_tool/utils/lexical_rand.py
ulid_tool/utils/misc.py
ulid_tool/utils/system_checks.py
ulid_tool-6.1.2.dist-info/licenses/LICENSE
ulid_tool-6.1.2.dist-info/METADATA
ulid_tool-6.1.2.dist-info/WHEEL
ulid_tool-6.1.2.dist-info/top_level.txt
ulid_tool-6.1.2.dist-info/RECORD
