Metadata-Version: 2.4
Name: ulid_tool
Version: 6.1.2
Summary: Minimalistic implementation of the ULID specification for python (https://github.com/ulid/spec). No integrated type or specification checks but system integrity check.
Author-email: "Adrian F. Hoefflin" <srccircumflex@outlook.com>
License: MIT License
Project-URL: Repository, https://github.com/srccircumflex/ulid_tool
Keywords: ulid
Classifier: Development Status :: 7 - Inactive
Classifier: Intended Audience :: Developers
Classifier: Topic :: Security :: Cryptography
Requires-Python: >=3.10
License-File: LICENSE
Requires-Dist: filelock
Dynamic: license-file
